systolic_array/2x2_matmul/rtl/mac_pe.v
module pe (
    input clk,
    input rst,
    input clear,
    input signed [7:0] a_in,
    input signed [7:0] b_in,
    output reg signed [7:0] a_out,
    output reg signed [7:0] b_out,
    output reg signed [17:0] c
);

    always @(posedge clk or posedge rst) begin
    
        if (rst) begin
            a_out <= 0;
            b_out <= 0;
            c <= 0;
        end 
        
        else if (clear) begin
            c <= 0;
            a_out <= a_in;
            b_out <= b_in;
        end 
        
        else begin
            c <= c + (a_in * b_in);
            a_out <= a_in;
            b_out <= b_in;
        end
        
    end

endmodule

systolic_array/2x2_matmul/rtl/systolic_array.v
`timescale 1ns / 1ps

module systolic_array (
    input clk,
    input rst,
    input clear,
    input signed [7:0] a1, a2,   
    input signed [7:0] b1, b2,  
    output signed [17:0] c11, c12, c21, c22
);

    wire signed [7:0] a11_to_12, a21_to_22;
    wire signed [7:0] b11_to_21, b12_to_22;


    // Row 1, Column 1
    pe pe11 (
        .clk(clk), .rst(rst), .clear(clear),
        .a_in(a1), .b_in(b1),
        .a_out(a11_to_12), .b_out(b11_to_21),
        .c(c11)
    );

    // Row 1, Column 2
    pe pe12 (
        .clk(clk), .rst(rst), .clear(clear),
        .a_in(a11_to_12), .b_in(b2),
        .a_out(), .b_out(b12_to_22),
        .c(c12)
    );

    // Row 2, Column 1
    pe pe21 (
        .clk(clk), .rst(rst), .clear(clear),
        .a_in(a2), .b_in(b11_to_21),
        .a_out(a21_to_22), .b_out(),
        .c(c21)
    );

    // Row 2, Column 2
    pe pe22 (
        .clk(clk), .rst(rst), .clear(clear),
        .a_in(a21_to_22), .b_in(b12_to_22),
        .a_out(), .b_out(),
        .c(c22)
    );

endmodule

systolic_array/2x2_matmul/rtl/systolic_array_tb.v
`timescale 1ns / 1ps

module systolic_array_tb;
    reg clk, rst, clear;
    reg signed [7:0] a1, a2;  
    reg signed [7:0] b1, b2; 
    wire signed [17:0] c11, c12, c21, c22;

    systolic_array dut (
        .clk(clk),
        .rst(rst),
        .clear(clear),
        .a1(a1),  
        .a2(a2),
        .b1(b1),   
        .b2(b2),
        .c11(c11), 
        .c12(c12),
        .c21(c21),
        .c22(c22)
    );

    initial begin
        clk = 0;
        forever #5 clk = ~clk;
    end

    initial begin
    $dumpfile("wave.vcd"); 
    $dumpvars(0, systolic_array_tb);  
    end
    
    initial begin

        rst = 1;
        clear = 0;
        
        a1 = 0; a2 = 0;
        b1 = 0; b2 = 0;
        
        #10 rst = 0;
        
        // clearing all c values 
        @(posedge clk);
        clear = 1;   // zero all c values
        @(posedge clk);
        clear = 0;   // release clear
        
        $display("\n========================================");
        $display("Starting Matrix Multiplication Test");
        $display("A = [1 2]\n    [3 4]\n\nB = [5 6]\n    [7 8]\n\n");
        $display("Expected C = [19 22]\n             [43 50]");
        $display("========================================\n");
        
        // Cycle 1
	@(posedge clk);
	a1 = 1;  b1 = 5;
	a2 = 0;  b2 = 0;

	// Cycle 2
	@(posedge clk);
	a1 = 2;  b1 = 7;
	a2 = 3;  b2 = 6;

	// Cycle 3
	@(posedge clk);
	a1 = 0;  b1 = 0;
	a2 = 4;  b2 = 8;

	// flush out data completely 
	@(posedge clk);
	a1 = 0;  b1 = 0;
	a2 = 0;  b2 = 0;

	// waiting for computation to get over
	repeat (3) @(posedge clk);
	
	// clearing all c values 
	@(posedge clk);
        clear = 1;  

        $display("\n========================================");
        $display("Final Results at T=%0t ns:", $time);
        $display("========================================");
        $display("C11 = %0d  (Expected: 19)", c11);
        $display("C12 = %0d  (Expected: 22)", c12);
        $display("C21 = %0d  (Expected: 43)", c21);
        $display("C22 = %0d  (Expected: 50)", c22);
        $display("========================================");
        
        if (c11 == 19 && c12 == 22 && c21 == 43 && c22 == 50) begin
            $display("PASSED!");
        end else begin
            $display("FAILED!");
        end
        $display("========================================\n");
        #20; 
        
        $finish;
    end
    
endmodule

systolic_array/2x2_matmul/simulation/wave.vcd
$date
	Tue Nov 11 21:26:54 2025
$end
$version
	Icarus Verilog
$end
$timescale
	1ps
$end
$scope module systolic_array_tb $end
$var wire 18 ! c22 [17:0] $end
$var wire 18 " c21 [17:0] $end
$var wire 18 # c12 [17:0] $end
$var wire 18 $ c11 [17:0] $end
$var reg 8 % a1 [7:0] $end
$var reg 8 & a2 [7:0] $end
$var reg 8 ' b1 [7:0] $end
$var reg 8 ( b2 [7:0] $end
$var reg 1 ) clear $end
$var reg 1 * clk $end
$var reg 1 + rst $end
$scope module dut $end
$var wire 8 , a1 [7:0] $end
$var wire 8 - a2 [7:0] $end
$var wire 8 . b1 [7:0] $end
$var wire 8 / b2 [7:0] $end
$var wire 1 ) clear $end
$var wire 1 * clk $end
$var wire 1 + rst $end
$var wire 18 0 c22 [17:0] $end
$var wire 18 1 c21 [17:0] $end
$var wire 18 2 c12 [17:0] $end
$var wire 18 3 c11 [17:0] $end
$var wire 8 4 b12_to_22 [7:0] $end
$var wire 8 5 b11_to_21 [7:0] $end
$var wire 8 6 a21_to_22 [7:0] $end
$var wire 8 7 a11_to_12 [7:0] $end
$scope module pe11 $end
$var wire 8 8 a_in [7:0] $end
$var wire 8 9 b_in [7:0] $end
$var wire 1 ) clear $end
$var wire 1 * clk $end
$var wire 1 + rst $end
$var reg 8 : a_out [7:0] $end
$var reg 8 ; b_out [7:0] $end
$var reg 18 < c [17:0] $end
$upscope $end
$scope module pe12 $end
$var wire 8 = a_in [7:0] $end
$var wire 8 > b_in [7:0] $end
$var wire 1 ) clear $end
$var wire 1 * clk $end
$var wire 1 + rst $end
$var reg 8 ? a_out [7:0] $end
$var reg 8 @ b_out [7:0] $end
$var reg 18 A c [17:0] $end
$upscope $end
$scope module pe21 $end
$var wire 8 B a_in [7:0] $end
$var wire 8 C b_in [7:0] $end
$var wire 1 ) clear $end
$var wire 1 * clk $end
$var wire 1 + rst $end
$var reg 8 D a_out [7:0] $end
$var reg 8 E b_out [7:0] $end
$var reg 18 F c [17:0] $end
$upscope $end
$scope module pe22 $end
$var wire 8 G a_in [7:0] $end
$var wire 8 H b_in [7:0] $end
$var wire 1 ) clear $end
$var wire 1 * clk $end
$var wire 1 + rst $end
$var reg 8 I a_out [7:0] $end
$var reg 8 J b_out [7:0] $end
$var reg 18 K c [17:0] $end
$upscope $end
$upscope $end
$upscope $end
$enddefinitions $end
#0
$dumpvars
b0 K
b0 J
b0 I
b0 H
b0 G
b0 F
b0 E
b0 D
b0 C
b0 B
b0 A
b0 @
b0 ?
b0 >
b0 =
b0 <
b0 ;
b0 :
b0 9
b0 8
b0 7
b0 6
b0 5
b0 4
b0 3
b0 2
b0 1
b0 0
b0 /
b0 .
b0 -
b0 ,
1+
0*
0)
b0 (
b0 '
b0 &
b0 %
b0 $
b0 #
b0 "
b0 !
$end
#5000
1*
#10000
0*
0+
#15000
1)
1*
#20000
0*
#25000
0)
1*
#30000
0*
#35000
b101 5
b101 ;
b101 C
b1 7
b1 :
b1 =
b101 $
b101 3
b101 <
b101 '
b101 .
b101 9
b1 %
b1 ,
b1 8
1*
#40000
0*
#45000
b101 E
b11 6
b11 D
b11 G
b1111 "
b1111 1
b1111 F
b110 4
b110 @
b110 H
b1 ?
b110 #
b110 2
b110 A
b111 5
b111 ;
b111 C
b10 7
b10 :
b10 =
b10011 $
b10011 3
b10011 <
b110 (
b110 /
b110 >
b11 &
b11 -
b11 B
b111 '
b111 .
b111 9
b10 %
b10 ,
b10 8
1*
#50000
0*
#55000
b0 5
b0 ;
b0 C
b0 7
b0 :
b0 =
b1000 4
b1000 @
b1000 H
b10 ?
b10110 #
b10110 2
b10110 A
b111 E
b100 6
b100 D
b100 G
b101011 "
b101011 1
b101011 F
b110 J
b11 I
b10010 !
b10010 0
b10010 K
b1000 (
b1000 /
b1000 >
b100 &
b100 -
b100 B
b0 '
b0 .
b0 9
b0 %
b0 ,
b0 8
1*
#60000
0*
#65000
b1000 J
b100 I
b110010 !
b110010 0
b110010 K
b0 E
b0 6
b0 D
b0 G
b0 4
b0 @
b0 H
b0 ?
b0 (
b0 /
b0 >
b0 &
b0 -
b0 B
1*
#70000
0*
#75000
b0 J
b0 I
1*
#80000
0*
#85000
1*
#90000
0*
#95000
1*
#100000
0*
#105000
b0 !
b0 0
b0 K
b0 "
b0 1
b0 F
b0 #
b0 2
b0 A
b0 $
b0 3
b0 <
1)
1*
